Metadata-Version: 2.4
Name: certbot-dns-ddnss
Version: 1.0.0
Summary: DDNSS.de DNS authenticator plugin for Certbot
Author-email: "A. Stamminger" <stammingers@gmail.com>
Project-URL: Source, https://github.com/astamminger/certbot-dns-ddnss
Project-URL: Documentation, https://github.com/astamminger/certbot-dns-ddnss/blob/main/README.md
Project-URL: Changelog, https://github.com/astamminger/certbot-dns-ddnss/blob/main/CHANGELOG.md
Classifier: Development Status :: 4 - Beta
Classifier: Programming Language :: Python :: 3
Classifier: Programming Language :: Python :: 3.9
Classifier: Programming Language :: Python :: 3.10
Classifier: Programming Language :: Python :: 3.11
Classifier: Programming Language :: Python :: 3.12
Classifier: License :: OSI Approved :: MIT License
Classifier: Topic :: Security
Classifier: Topic :: Internet :: WWW/HTTP
Classifier: Topic :: Utilities
Requires-Python: >=3.9
License-File: LICENSE
Requires-Dist: certbot
Provides-Extra: tests
Requires-Dist: pre-commit; extra == "tests"
Requires-Dist: pytest; extra == "tests"
Requires-Dist: pytest-cov; extra == "tests"
Requires-Dist: mypy; extra == "tests"
Dynamic: license-file
